{
  "generated_at": "2026-07-19T11:28:17+09:00",
  "fukuoka_query_product_pool": 180,
  "status_counts": {
    "unresolved_tour_query_pool": 126,
    "confirmed_fukuoka_city_content": 12,
    "outside_or_multi_region": 29,
    "confirmed_fukuoka_city": 13
  },
  "non_tour_products": 42,
  "non_tour_manual_review_complete": true,
  "missing_non_tour_review_ids": [],
  "stale_non_tour_review_ids": [],
  "interpretation": "180 is a search-result audit pool, not a count of Fukuoka City supply. Unresolved tours are not counted as city-confirmed content."
}