{
  "result": {
    "content": [
      {
        "type": "text",
        "text": "{\n  \"widget\": {\n    \"type\": \"ListView\",\n    \"children\": [\n      {\n        \"type\": \"ListViewItem\",\n        \"children\": [\n          {\n            \"type\": \"Box\",\n            \"direction\": \"row\",\n            \"children\": [\n              {\n                \"type\": \"Col\",\n                \"children\": [\n                  {\n                    \"type\": \"Title\",\n                    \"value\": \"[예약 즉시 확정] 입장권 - 성인\",\n                    \"size\": \"md\",\n                    \"weight\": \"bold\"\n                  },\n                  {\n                    \"type\": \"Text\",\n                    \"value\": \"<p>[이 티켓의 매력 포인트!]<br/>• 박물관에는 원자폭탄의 참상과 과정, 핵무기 개발의 역사 등을 이야기하는 전시물이 있습니다.<br/>• 원자폭탄 피해에 관한 대규모 자료...\",\n                    \"weight\": \"medium\",\n                    \"size\": \"sm\",\n                    \"color\": {\n                      \"dark\": \"#AAAAAA\",\n                      \"light\": \"#777777\"\n                    }\n                  },\n                  {\n                    \"type\": \"Text\",\n                    \"value\": \"⭐ 4 (리뷰 1개)\",\n                    \"weight\": \"medium\",\n                    \"size\": \"sm\"\n                  },\n                  {\n                    \"type\": \"Button\",\n                    \"label\": \"마이리얼트립에서 보기\",\n                    \"onClickAction\": {\n                      \"type\": \"open_url\",\n                      \"payload\": {\n                        \"target\": {\n                          \"url\": \"https://www.myrealtrip.com/traveler-experiences/5542787\"\n                        }\n                      },\n                      \"handler\": \"client\",\n                      \"loadingBehavior\": \"none\",\n                      \"url\": \"https://www.myrealtrip.com/traveler-experiences/5542787\"\n                    },\n                    \"style\": \"primary\",\n                    \"size\": \"sm\"\n                  }\n                ],\n                \"gap\": 6,\n                \"flex\": 1\n              }\n            ],\n            \"gap\": 3,\n            \"padding\": {\n              \"x\": 4,\n              \"y\": 3\n            },\n            \"background\": {\n              \"dark\": \"#2A2A2A\",\n              \"light\": \"#FFFFFF\"\n            },\n            \"radius\": \"xl\",\n            \"width\": \"100%\",\n            \"align\": \"start\"\n          }\n        ]\n      },\n      {\n        \"type\": \"ListViewItem\",\n        \"children\": [\n          {\n            \"type\": \"Box\",\n            \"direction\": \"row\",\n            \"children\": [\n              {\n                \"type\": \"Col\",\n                \"children\": [\n                  {\n                    \"type\": \"Title\",\n                    \"value\": \"✅ 포함 사항\",\n                    \"size\": \"md\",\n                    \"weight\": \"bold\"\n                  },\n                  {\n                    \"type\": \"Text\",\n                    \"value\": \"• • 나가사키 원폭자료관 입장권\",\n                    \"weight\": \"medium\",\n                    \"size\": \"sm\"\n                  }\n                ],\n                \"gap\": 2,\n                \"flex\": 1\n              }\n            ],\n            \"gap\": 8,\n            \"padding\": {\n              \"x\": 4,\n              \"y\": 3\n            },\n            \"background\": {\n              \"dark\": \"#2A2A2A\",\n              \"light\": \"#FFFFFF\"\n            },\n            \"radius\": \"xl\",\n            \"width\": \"100%\",\n            \"align\": \"start\"\n          }\n        ]\n      },\n      {\n        \"type\": \"ListViewItem\",\n        \"children\": [\n          {\n            \"type\": \"Box\",\n            \"direction\": \"row\",\n            \"children\": [\n              {\n                \"type\": \"Col\",\n                \"children\": [\n                  {\n                    \"type\": \"Title\",\n                    \"value\": \"❌ 불포함 사항\",\n                    \"size\": \"md\",\n                    \"weight\": \"bold\"\n                  },\n                  {\n                    \"type\": \"Text\",\n                    \"value\": \"• • 식사 및 음료\\r\\n• 기타 개인 경비\",\n                    \"weight\": \"medium\",\n                    \"size\": \"sm\"\n                  }\n                ],\n                \"gap\": 2,\n                \"flex\": 1\n              }\n            ],\n            \"gap\": 8,\n            \"padding\": {\n              \"x\": 4,\n              \"y\": 3\n            },\n            \"background\": {\n              \"dark\": \"#2A2A2A\",\n              \"light\": \"#FFFFFF\"\n            },\n            \"radius\": \"xl\",\n            \"width\": \"100%\",\n            \"align\": \"start\"\n          }\n        ]\n      },\n      {\n        \"type\": \"ListViewItem\",\n        \"children\": [\n          {\n            \"type\": \"Box\",\n            \"direction\": \"row\",\n            \"children\": [\n              {\n                \"type\": \"Col\",\n                \"children\": [\n                  {\n                    \"type\": \"Title\",\n                    \"value\": \"📍 이용 안내\",\n                    \"size\": \"md\",\n                    \"weight\": \"bold\"\n                  },\n                  {\n                    \"type\": \"Text\",\n                    \"value\": \"시간: [9월 - 4월] 8:30-17:30\\r\\n[5월 - 8월] 8:30-18:30\\r\\n[8월 7일 - 9일] 8:30-20:00\\r\\n•입장 마감: 마감 시간 30분 전\\r\\n•휴관일 : 12월 29일 ~ 12월 31일\\r\\n※자세한 운영시간은 링크(https://nabmuseum.jp/genbaku/)를 확인해주세요.\",\n                    \"weight\": \"medium\",\n                    \"size\": \"sm\"\n                  },\n                  {\n                    \"type\": \"Text\",\n                    \"value\": \"장소: (우)852-8117 나가사키현 나가사키시 히라노초 7-8\",\n                    \"weight\": \"medium\",\n                    \"size\": \"sm\"\n                  }\n                ],\n                \"gap\": 2,\n                \"flex\": 1\n              }\n            ],\n            \"gap\": 8,\n            \"padding\": {\n              \"x\": 4,\n              \"y\": 3\n            },\n            \"background\": {\n              \"dark\": \"#2A2A2A\",\n              \"light\": \"#FFFFFF\"\n            },\n            \"radius\": \"xl\",\n            \"width\": \"100%\",\n            \"align\": \"start\"\n          }\n        ]\n      },\n      {\n        \"type\": \"ListViewItem\",\n        \"children\": [\n          {\n            \"type\": \"Box\",\n            \"direction\": \"row\",\n            \"children\": [\n              {\n                \"type\": \"Col\",\n                \"children\": [\n                  {\n                    \"type\": \"Title\",\n                    \"value\": \"🔄 취소 정책\",\n                    \"size\": \"md\",\n                    \"weight\": \"bold\"\n                  },\n                  {\n                    \"type\": \"Caption\",\n                    \"value\": \"옵션 별로 취소/환불 정책이 상이할 수 있습니다.\\n옵션 선택 후 상세 정책을 확인해주세요.\",\n                    \"size\": \"md\",\n                    \"weight\": \"medium\",\n                    \"color\": {\n                      \"dark\": \"#999999\",\n                      \"light\": \"#666666\"\n                    }\n                  }\n                ],\n                \"gap\": 2,\n                \"flex\": 1\n              }\n            ],\n            \"gap\": 8,\n            \"padding\": {\n              \"x\": 4,\n              \"y\": 3\n            },\n            \"background\": {\n              \"dark\": \"#2A2A2A\",\n              \"light\": \"#FFFFFF\"\n            },\n            \"radius\": \"xl\",\n            \"width\": \"100%\",\n            \"align\": \"start\"\n          }\n        ]\n      }\n    ],\n    \"limit\": 10\n  },\n  \"name\": \"myrealtrip\",\n  \"copy_text\": \"**[예약 즉시 확정] 입장권 - 성인**\\n⭐ 4 (리뷰 1개)\\n<p>[이 티켓의 매력 포인트!]<br/>• 박물관에는 원자폭탄의 참상과 과정, 핵무기 개발의 역사 등을 이야기하는 전시물이 있습니다.<br/>• 원자폭탄 피해에 관한 대규모 자료...\\n**포함 사항**\\n• • 나가사키 원폭자료관 입장권\\n**불포함 사항**\\n• • 식사 및 음료\\r\\n• 기타 개인 경비\\n🔗 https://www.myrealtrip.com/traveler-experiences/5542787\"\n}"
      }
    ]
  },
  "jsonrpc": "2.0",
  "id": 5542787
}