{
  "source": "full_next_data",
  "hydration_query_count": 2,
  "itineraries": [
    {
      "itineraryId": 26764,
      "title": "코스1",
      "slots": [
        {
          "title": "08:00 하카타역 치쿠시구치",
          "description": "집합 장소에는 반드시 10분 일찍 도착해 주세요. 협조해 주셔서 감사합니다.지각하거나 미참석하시는 경우 환불이 어렵습니다.",
          "imageUrl": "https://dry7pvlp22cox.cloudfront.net/mrt-images-prod/2026/03/26/WnAI/2xACrdm9iC.jpg",
          "place": {
            "coordinate": {
              "lat": 33.5897928,
              "lng": 130.4233148
            },
            "label": "로손"
          }
        },
        {
          "title": "10:00 벳푸 우미 지고쿠 온천",
          "description": "벳푸 8대 지옥 온천 중 가장 규모가 큰 명소로, 보석처럼 짙푸른 색을 띠는 고온 온천수가 인상적입니다. 피어오르는 수증기가 어우러져 마치 신비로운 선경에 들어온 듯한 분위기를 자아냅니다. 햇살 아래에서는 투명한 코발트 블루 빛이 반짝이며, 마치 하늘을 그대로 담아낸 듯해 사진을 찍기만 해도 필터를 씌운 것 같은 감성을 느낄 수 있습니다.\n\n또한 인근에서는 온천 증기로 만든 달걀을 맛볼 수 있으며, 부드럽고 촉촉한 식감에 은은한 향이 더해져 특별한 별미를 즐기실 수 있습니다.",
          "imageUrl": "https://dry7pvlp22cox.cloudfront.net/mrt-images-prod/2026/03/26/Fyge/gy5JEjjJu6.jpg",
          "duration": "30분 소요",
          "place": {
            "coordinate": {
              "lat": 33.3168115,
              "lng": 131.4687384
            },
            "label": "우미 지고쿠 (바다지옥)"
          }
        },
        {
          "title": "11:00 유후다케",
          "description": "사기리다이를 경유하며, 이곳에서 유후다케의 아름다운 전경을 감상하실 수 있습니다.\n\n(불가항력적인 상황—겨울철 도로 결빙, 고속도로 통제 등—이 발생할 경우 안전을 위해 해당 관광지는 취소되며, 유후인 자유시간이 30분 연장됩니다.)",
          "imageUrl": "https://dry7pvlp22cox.cloudfront.net/mrt-images-prod/2026/03/26/AhwG/roZdt96o31.jpg",
          "duration": "10분 소요",
          "place": {
            "coordinate": {
              "lat": 33.2653153,
              "lng": 131.396025
            },
            "label": "유후다케 등산로 입구"
          }
        },
        {
          "title": "12:00 큐슈 자연동물원",
          "description": "큐슈 자연동물원 입장료는 포함되어 있지 않습니다.\n(성인 2,600엔 / 아동 1,500엔)\n\n⚠️ 악천후로 인해 큐슈 자연동물원이 휴장할 경우, 일정은 우미노나카미치 수족관으로 대체됩니다.\n입장료: 성인 2,500엔 / 초·중학생 1,200엔 / 유아 700엔\n\n당일 참가 인원 또는 날씨 상황에 따라 일정이 조정될 수 있으며, 일부 관광지만 방문할 수 있습니다.",
          "imageUrl": "https://dry7pvlp22cox.cloudfront.net/mrt-images-prod/2026/03/26/4Swm/RgjhN7yAhS.jpg",
          "duration": "2시간 소요",
          "place": {
            "coordinate": {
              "lat": 33.2582855,
              "lng": 131.5328036
            },
            "label": "다카사키야마 자연동물원"
          }
        },
        {
          "title": "14:30 유후인 + 긴린코",
          "description": "유후인 온천은 일본 오이타현 유후시 유후인초에 위치한 온천 지역입니다. 유후인역에서 온천 지역 방향으로 이어지는 길은 ‘유후미도리’라고 불리며, 긴린코 호수까지 이어지는 구간은 ‘유노쓰보 거리’로도 알려져 있습니다. 이 지역에는 다양한 잡화점, 레스토랑, 미술관 등이 모여 있어 여유롭게 산책하며 즐기기 좋은 곳입니다.\n\n당일 참가 인원 또는 날씨 상황에 따라 일정이 조정될 수 있으며, 일부 관광지만 방문할 수 있습니다.",
          "imageUrl": "https://dry7pvlp22cox.cloudfront.net/mrt-images-prod/2026/03/26/Hcar/z6o3rL8H1u.jpg",
          "duration": "2시간 소요",
          "place": {
            "coordinate": {
              "lat": 33.2626697,
              "lng": 131.355101
            },
            "label": "유후인역"
          }
        },
        {
          "title": "18:30 하카타역 치쿠시 출구",
          "description": "실제 귀환 시간은 당일 도로 상황에 따라 달라질 수 있으며, 정확한 도착 시간은 보장되지 않습니다.\n저녁 식사 예약이나 비행기, 신칸센 등 이동 일정은 잡지 말아주시기 바랍니다. 양해 부탁드립니다.",
          "imageUrl": "https://dry7pvlp22cox.cloudfront.net/mrt-images-prod/2026/03/26/gt4Q/vPTAwbwCCc.jpg",
          "place": {
            "coordinate": {
              "lat": 33.5897928,
              "lng": 130.4233148
            },
            "label": "로손"
          }
        }
      ]
    }
  ]
}